straph/__init__.py
straph/stream.py
straph/components/UnionFindSCC.py
straph/components/__init__.py
straph/components/component.py
straph/components/stable_connected_component.py
straph/components/strongly_connected_component.py
straph/components/weakly_connected_component.py
straph/dags/__init__.py
straph/dags/condensation_dag.py
straph/dags/dag.py
straph/dags/stable_dag.py
straph/etf/ChainedTreap.py
straph/etf/EulerTourForest.py
straph/etf/EulerTourTree.py
straph/etf/__init__.py
straph/generators/__init__.py
straph/generators/barabasi_albert.py
straph/generators/erdos_renyi.py
straph/parser/__init__.py
straph/parser/parser.py
straph/paths/__init__.py
straph/paths/path_object.py
straph/paths/paths.py
straph/utils/__init__.py
straph-0.3.dist-info/LICENSE.txt
straph-0.3.dist-info/METADATA
straph-0.3.dist-info/WHEEL
straph-0.3.dist-info/top_level.txt
straph-0.3.dist-info/RECORD
