Metadata-Version: 2.1
Name: straph
Version: 0.3
Summary: Straph is a python package to modelize, analyze and visualize Stream Graphs, Link Streams and Temporal Networks.
Home-page: https://github.com/StraphX/Straph
Author: Leo Rannou
Author-email: leo.rannou@gmail.com
License: Apache 2.0
Platform: UNKNOWN
Classifier: Development Status :: 3 - Alpha
Classifier: Intended Audience :: Science/Research
Classifier: Programming Language :: Python :: 3
Classifier: License :: OSI Approved :: Apache Software License
Classifier: Operating System :: OS Independent
Requires-Python: >=3.6
